{
  "id": 576,
  "name": "Scarecrow",
  "slug": "576-scarecrow",
  "powerstats": {
    "intelligence": 81,
    "strength": 10,
    "speed": 12,
    "durability": 14,
    "power": 48,
    "combat": 50
  },
  "appearance": {
    "gender": "Male",
    "race": "Human",
    "height": [
      "6'0",
      "183 cm"
    ],
    "weight": [
      "140 lb",
      "63 kg"
    ],
    "eyeColor": "Blue",
    "hairColor": "Brown"
  },
  "biography": {
    "fullName": "Jonathan Crane",
    "alterEgos": "No alter egos found.",
    "aliases": [
      "-"
    ],
    "placeOfBirth": "-",
    "firstAppearance": "WORLD'S FINEST COMICS #3 (Fall, 1941)",
    "publisher": "DC Comics",
    "alignment": "bad"
  },
  "work": {
    "occupation": "Special Professional Criminal",
    "base": "Gotham City"
  },
  "connections": {
    "groupAffiliation": "Injustice Gang",
    "relatives": "-"
  },
  "images": {
    "xs": "https://cdn.jsdelivr.net/gh/akabab/superhero-api@0.3.0/api/images/xs/576-scarecrow.jpg",
    "sm": "https://cdn.jsdelivr.net/gh/akabab/superhero-api@0.3.0/api/images/sm/576-scarecrow.jpg",
    "md": "https://cdn.jsdelivr.net/gh/akabab/superhero-api@0.3.0/api/images/md/576-scarecrow.jpg",
    "lg": "https://cdn.jsdelivr.net/gh/akabab/superhero-api@0.3.0/api/images/lg/576-scarecrow.jpg"
  }
}