{
  "id": 683,
  "name": "Valerie Hart",
  "powerstats": {
    "intelligence": null,
    "strength": null,
    "speed": null,
    "durability": null,
    "power": null,
    "combat": null
  },
  "biography": {
    "fullName": "",
    "alterEgos": "No alter egos found.",
    "aliases": [
      "-"
    ],
    "placeOfBirth": "East Coast, Canada",
    "firstAppearance": "Team Epic Episode 101",
    "publisher": "Team Epic TV",
    "alignment": "good"
  },
  "appearance": {
    "gender": "Female",
    "race": null,
    "height": [
      "5'9",
      "175 cm"
    ],
    "weight": [
      "125 lb",
      "56 kg"
    ],
    "eyeColor": "Hazel",
    "hairColor": "Black"
  },
  "work": {
    "occupation": "Vigilante, Superhero",
    "base": "Toronto"
  },
  "connections": {
    "groupAffiliation": "Team Epic",
    "relatives": "-"
  },
  "image": {
    "url": "https://akabab.github.io/superhero-api/api/images/sm/valerie-hart.jpg"
  }
}