{
  "id": 663,
  "name": "Thunderbird III",
  "slug": "663-thunderbird-iii",
  "powerstats": {
    "intelligence": null,
    "strength": null,
    "speed": null,
    "durability": null,
    "power": null,
    "combat": null
  },
  "appearance": {
    "gender": "Male",
    "race": null,
    "height": [
      "5'9'",
      "175 cm"
    ],
    "weight": [
      "165 lb",
      "74 kg"
    ],
    "eyeColor": "Brown",
    "hairColor": "Black"
  },
  "biography": {
    "fullName": "Neal Shaara",
    "alterEgos": "No alter egos found.",
    "aliases": [
      "-"
    ],
    "placeOfBirth": "Bangladesh",
    "firstAppearance": "-",
    "publisher": "Marvel Comics",
    "alignment": "good"
  },
  "work": {
    "occupation": "Adventurer",
    "base": "-"
  },
  "connections": {
    "groupAffiliation": "None; formerly X-Men, X-Corporation",
    "relatives": "Sanjit (brother,deceased)"
  }
}